{
  "battle": "0xe71bdd5249b1e757d752d45ea510274ef4644eec",
  "seed": 20260303,
  "lastProcessedTurn": 79,
  "lastSubmitBlock": 38288008,
  "prevNcc": {
    "A": {
      "salt": "0xdf1e23d281fe3d0033bb41926759a204352ee60346f55c4f475224cfac4918ff",
      "intendedIdx": 0,
      "candidates": [
        "abandon",
        "ability",
        "abstract",
        "act"
      ]
    },
    "B": {
      "salt": "0x267b2733ca0d48c6a891940cf072c387f5e4ad070380579a1beabdccf74b60c5",
      "intendedIdx": 0,
      "candidates": [
        "abandon",
        "absorb",
        "able",
        "across"
      ]
    }
  },
  "results": [
    {
      "turn": 0,
      "agent": "A",
      "gas": "1076277",
      "bankA": "400",
      "bankB": "400",
      "targetWord": "basic",
      "nccGuessCorrect": false,
      "vopAttempts": 0,
      "txHash": "0xf20b9e4872b39e3ad5019cc97105c278cea9e88a6ee176e48bf0d478eb9b62f6"
    },
    {
      "turn": 1,
      "agent": "B",
      "gas": "1765209",
      "bankA": "314",
      "bankB": "400",
      "targetWord": "tragic",
      "nccGuessCorrect": true,
      "vopAttempts": 418,
      "txHash": "0x81d7b0c4e4d72d4214abc521cd4ab877dbb4f60596069fe4c6fe7843e065797a"
    },
    {
      "turn": 2,
      "agent": "A",
      "gas": "1433440",
      "bankA": "314",
      "bankB": "393",
      "targetWord": "wild",
      "nccGuessCorrect": true,
      "vopAttempts": 47,
      "txHash": "0x839e7e46f24ef0550d0b363d276f682accba068031f072398aa1fb18f0860942"
    },
    {
      "turn": 3,
      "agent": "B",
      "gas": "898512",
      "bankA": "308",
      "bankB": "393",
      "targetWord": "mobile",
      "nccGuessCorrect": false,
      "vopAttempts": 6960,
      "txHash": "0xa0900a380938fbcbbfe96373c1f3a54cf0998dc708d96453d5b9b7651ebe748d"
    },
    {
      "turn": 4,
      "agent": "A",
      "gas": "482182",
      "bankA": "308",
      "bankB": "386",
      "targetWord": "chronic",
      "nccGuessCorrect": true,
      "vopAttempts": 2079,
      "txHash": "0x14a55394cf979fce858c2f72c6b0f3be959eb96bee78c1e082a0566966ef2c8c"
    },
    {
      "turn": 5,
      "agent": "B",
      "gas": "731104",
      "bankA": "302",
      "bankB": "386",
      "targetWord": "asthma",
      "nccGuessCorrect": true,
      "vopAttempts": 29,
      "txHash": "0xb3cbc07737adcb750ef92cb781b2de3c1643713b2620617396c73d4df93a8049"
    },
    {
      "turn": 6,
      "agent": "A",
      "gas": "1208878",
      "bankA": "302",
      "bankB": "351",
      "targetWord": "hip",
      "nccGuessCorrect": true,
      "vopAttempts": 335,
      "txHash": "0x664e8922106f4416e83aca576dbc6971b1860d0ed55e56164a8ccd56ad3c99b8"
    },
    {
      "turn": 7,
      "agent": "B",
      "gas": "1396028",
      "bankA": "297",
      "bankB": "351",
      "targetWord": "stamp",
      "nccGuessCorrect": true,
      "vopAttempts": 695,
      "txHash": "0x8b5202184b5a5e41294640677552d77c7b590883bae407c0268620be453693cf"
    },
    {
      "turn": 8,
      "agent": "A",
      "gas": "994887",
      "bankA": "292",
      "bankB": "345",
      "targetWord": "news",
      "nccGuessCorrect": true,
      "vopAttempts": 186,
      "txHash": "0xbf1eef8b6c72ce213f2854aa374d86201a7df394b96e6b58214e931a67efb0b2"
    },
    {
      "turn": 9,
      "agent": "B",
      "gas": "863778",
      "bankA": "292",
      "bankB": "345",
      "targetWord": "frame",
      "nccGuessCorrect": false,
      "vopAttempts": 351,
      "txHash": "0xce65e5a1c08d9b56d0d2d4f72e94e14f5d49f389c76502d887e93d43488780e8"
    },
    {
      "turn": 10,
      "agent": "A",
      "gas": "907964",
      "bankA": "292",
      "bankB": "339",
      "targetWord": "evil",
      "nccGuessCorrect": true,
      "vopAttempts": 2933,
      "txHash": "0x8bde48f6302024603243777a4cc7f4807e6d2bbd09e194c015dff9056aeff5eb"
    },
    {
      "turn": 11,
      "agent": "B",
      "gas": "911292",
      "bankA": "287",
      "bankB": "339",
      "targetWord": "lounge",
      "nccGuessCorrect": true,
      "vopAttempts": 2417,
      "txHash": "0x718014e4bc6a32ee2e50d4b1abe27a1d7ffffdd8895ed627e4d50791c1ff61c5"
    },
    {
      "turn": 12,
      "agent": "A",
      "gas": "982883",
      "bankA": "282",
      "bankB": "305",
      "targetWord": "curtain",
      "nccGuessCorrect": true,
      "vopAttempts": 610,
      "txHash": "0xdc94bbb3099e7297ebb169a63950a9df4c8b330279f3714a23bc6f0250c30dc1"
    },
    {
      "turn": 13,
      "agent": "B",
      "gas": "1073263",
      "bankA": "282",
      "bankB": "305",
      "targetWord": "reject",
      "nccGuessCorrect": true,
      "vopAttempts": 1260,
      "txHash": "0x9ed9210f626d5a72bb8401dad23c55781ac72b67808a50942efe033546d9e07a"
    },
    {
      "turn": 14,
      "agent": "A",
      "gas": "716382",
      "bankA": "282",
      "bankB": "300",
      "targetWord": "dog",
      "nccGuessCorrect": true,
      "vopAttempts": 34,
      "txHash": "0xf572229acc70929b96ea017a6725e302b104fb1e16c81b58fef4afcef29ecb97"
    },
    {
      "turn": 15,
      "agent": "B",
      "gas": "966164",
      "bankA": "277",
      "bankB": "300",
      "targetWord": "evil",
      "nccGuessCorrect": true,
      "vopAttempts": 3186,
      "txHash": "0x17885551bb5cc7ac8eaac629d2e81cb0ba1a0717b443698318fc3fcea6f29862"
    },
    {
      "turn": 16,
      "agent": "A",
      "gas": "911722",
      "bankA": "277",
      "bankB": "295",
      "targetWord": "link",
      "nccGuessCorrect": true,
      "vopAttempts": 1753,
      "txHash": "0xc52a8fa71f698294cf863be0df082ab55fee78797e98fd3c84aecc1bd46abbde"
    },
    {
      "turn": 17,
      "agent": "B",
      "gas": "772179",
      "bankA": "272",
      "bankB": "295",
      "targetWord": "fall",
      "nccGuessCorrect": true,
      "vopAttempts": 256,
      "txHash": "0xbeb0c78ab3fed6aba50c9d009f0dc40a0459b45c9c7e3b9a65521f98b85b8166"
    },
    {
      "turn": 18,
      "agent": "A",
      "gas": "1176483",
      "bankA": "272",
      "bankB": "290",
      "targetWord": "dawn",
      "nccGuessCorrect": true,
      "vopAttempts": 1709,
      "txHash": "0x9e883ca320fb22a72481a9e87b8e1cabefc59ce4f236247b019e9a81f6732ac0"
    },
    {
      "turn": 19,
      "agent": "B",
      "gas": "1758759",
      "bankA": "267",
      "bankB": "290",
      "targetWord": "wing",
      "nccGuessCorrect": true,
      "vopAttempts": 588,
      "txHash": "0xc493785bdaf0702d28383a322ffe88c28fff945f9ad53954769d5082510754c4"
    },
    {
      "turn": 20,
      "agent": "A",
      "gas": "1396750",
      "bankA": "267",
      "bankB": "285",
      "targetWord": "vendor",
      "nccGuessCorrect": true,
      "vopAttempts": 24,
      "txHash": "0xc02b21c49560c932d3b4cd8f19a7635e7a265edad705f011ff2f90fa5c9b2716"
    },
    {
      "turn": 21,
      "agent": "B",
      "gas": "956878",
      "bankA": "262",
      "bankB": "285",
      "targetWord": "moon",
      "nccGuessCorrect": false,
      "vopAttempts": 659,
      "txHash": "0x3cd57b7b01d2f6ddb225159352903c20bae8aaa007be7a0cdb6190ed76ea7062"
    },
    {
      "turn": 22,
      "agent": "A",
      "gas": "827343",
      "bankA": "262",
      "bankB": "280",
      "targetWord": "detect",
      "nccGuessCorrect": true,
      "vopAttempts": 900,
      "txHash": "0x52999ddeff7da25ba7b2ac3d91547c92553165c7c7d437899422ba84ab1b768c"
    },
    {
      "turn": 23,
      "agent": "B",
      "gas": "1211754",
      "bankA": "257",
      "bankB": "280",
      "targetWord": "job",
      "nccGuessCorrect": true,
      "vopAttempts": 3,
      "txHash": "0xbdbc77fe9b373fa95cd08131abfefbbd7e91d5804f0749578bc18ef07a8e008b"
    },
    {
      "turn": 24,
      "agent": "A",
      "gas": "1242101",
      "bankA": "257",
      "bankB": "247",
      "targetWord": "rare",
      "nccGuessCorrect": true,
      "vopAttempts": 1157,
      "txHash": "0x3f108b4edf1ac169ebcc09723f54c6b803d4ccaaa9e2feece82664ab0ad0f8bc"
    },
    {
      "turn": 25,
      "agent": "B",
      "gas": "1284871",
      "bankA": "253",
      "bankB": "247",
      "targetWord": "office",
      "nccGuessCorrect": true,
      "vopAttempts": 289,
      "txHash": "0xad16180317856d1eaeda449c2471a1d1a9c620205e0cc9c070c4ea5e36375519"
    },
    {
      "turn": 26,
      "agent": "A",
      "gas": "1228233",
      "bankA": "253",
      "bankB": "243",
      "targetWord": "pond",
      "nccGuessCorrect": true,
      "vopAttempts": 2905,
      "txHash": "0xe01838721cf4d1b77d7efe445f905ef9fa6ef5af16d50d2a7d8583b107f09726"
    },
    {
      "turn": 27,
      "agent": "B",
      "gas": "1491334",
      "bankA": "249",
      "bankB": "239",
      "targetWord": "paddle",
      "nccGuessCorrect": true,
      "vopAttempts": 337,
      "txHash": "0x0bed2d2778b82219cf5a26e5cfa253490a0d53c66b2d3f1dd0ac25960e6ac721"
    },
    {
      "turn": 28,
      "agent": "A",
      "gas": "1201469",
      "bankA": "249",
      "bankB": "239",
      "targetWord": "uncover",
      "nccGuessCorrect": true,
      "vopAttempts": 1007,
      "txHash": "0xaa51deed5cd2a305b1015f10bfaba133f2e5ba9c3359e54be9b8f0c3fbe632c7"
    },
    {
      "turn": 29,
      "agent": "B",
      "gas": "1279832",
      "bankA": "245",
      "bankB": "239",
      "targetWord": "evolve",
      "nccGuessCorrect": true,
      "vopAttempts": 837,
      "txHash": "0xe6e38731b37d0c38c914c0182378653e1377dac1f5ca30701cd29038a758e0dc"
    },
    {
      "turn": 30,
      "agent": "A",
      "gas": "1548435",
      "bankA": "245",
      "bankB": "235",
      "targetWord": "vapor",
      "nccGuessCorrect": true,
      "vopAttempts": 42,
      "txHash": "0x8311e0ce20d2b0bea3ad18067c9513ef94f4b91abcea0361ada3c20e74b37fad"
    },
    {
      "turn": 31,
      "agent": "B",
      "gas": "948778",
      "bankA": "241",
      "bankB": "235",
      "targetWord": "shrug",
      "nccGuessCorrect": true,
      "vopAttempts": 2449,
      "txHash": "0xa6261a6b7542ca98693f85bed40da223884aa789ef4a9be1eef11a8abca6c814"
    },
    {
      "turn": 32,
      "agent": "A",
      "gas": "877155",
      "bankA": "241",
      "bankB": "231",
      "targetWord": "access",
      "nccGuessCorrect": true,
      "vopAttempts": 417,
      "txHash": "0x7041303a00fbb66277a59408be9602d5a8ae8c3bea3cbfe22333ea9125e8b6f0"
    },
    {
      "turn": 33,
      "agent": "B",
      "gas": "1402433",
      "bankA": "237",
      "bankB": "227",
      "targetWord": "service",
      "nccGuessCorrect": false,
      "vopAttempts": 495,
      "txHash": "0xb72c776f0de2b4aef08958bf5d0af494e74e45be0d99226dab54712923a55b14"
    },
    {
      "turn": 34,
      "agent": "A",
      "gas": "1117134",
      "bankA": "237",
      "bankB": "227",
      "targetWord": "plastic",
      "nccGuessCorrect": true,
      "vopAttempts": 500,
      "txHash": "0x6ad7e06bc3a4eacb54c145d53971be566307880d5a0e157d462615f02ab1e5d2"
    },
    {
      "turn": 35,
      "agent": "B",
      "gas": "1275194",
      "bankA": "233",
      "bankB": "227",
      "targetWord": "isolate",
      "nccGuessCorrect": true,
      "vopAttempts": 228,
      "txHash": "0xcaea249c1c0d013d89f1420ece42cda452c924ed7eaeef3acf4f7f8b58047f2b"
    },
    {
      "turn": 36,
      "agent": "A",
      "gas": "889033",
      "bankA": "233",
      "bankB": "195",
      "targetWord": "shield",
      "nccGuessCorrect": true,
      "vopAttempts": 829,
      "txHash": "0xedbb61e8fba7d94cc13a2194103f59e279406e809ae8584d331df325eb9c6a94"
    },
    {
      "turn": 37,
      "agent": "B",
      "gas": "840905",
      "bankA": "229",
      "bankB": "192",
      "targetWord": "aisle",
      "nccGuessCorrect": true,
      "vopAttempts": 478,
      "txHash": "0x31ce798b78e79ee5bd46c46997ddd81720e29e73d4ad62029fc5f0d1a275abb0"
    },
    {
      "turn": 38,
      "agent": "A",
      "gas": "1334640",
      "bankA": "229",
      "bankB": "192",
      "targetWord": "original",
      "nccGuessCorrect": true,
      "vopAttempts": 52,
      "txHash": "0x9192fe55996fbc12e94bc6da0ec59684c3701623c6dd641565137fd8db70abf7"
    },
    {
      "turn": 39,
      "agent": "B",
      "gas": "1027258",
      "bankA": "225",
      "bankB": "192",
      "targetWord": "soda",
      "nccGuessCorrect": false,
      "vopAttempts": 900,
      "txHash": "0x9202a89b92ef0143e908edbb2c793c7d77852dce71cf98b7ca3d026704e94bc5"
    },
    {
      "turn": 40,
      "agent": "A",
      "gas": "977410",
      "bankA": "225",
      "bankB": "189",
      "targetWord": "blade",
      "nccGuessCorrect": true,
      "vopAttempts": 224,
      "txHash": "0x699b288526ae91af3bc21b4a8f790ffe88b60b945302c6b04c9b27a56e634533"
    },
    {
      "turn": 41,
      "agent": "B",
      "gas": "1436569",
      "bankA": "221",
      "bankB": "189",
      "targetWord": "square",
      "nccGuessCorrect": true,
      "vopAttempts": 3555,
      "txHash": "0x9edbc6936cb79df383c159d15a444f3d2ad504bf2ac9067733b42a585a9a5b1c"
    },
    {
      "turn": 42,
      "agent": "A",
      "gas": "1135492",
      "bankA": "221",
      "bankB": "158",
      "targetWord": "piano",
      "nccGuessCorrect": true,
      "vopAttempts": 121,
      "txHash": "0xea9f56f5bdd11e9a788215f5b74feeeb2a08a6bd3602a7f3ea90258edbe45e5e"
    },
    {
      "turn": 43,
      "agent": "B",
      "gas": "980983",
      "bankA": "217",
      "bankB": "158",
      "targetWord": "lens",
      "nccGuessCorrect": false,
      "vopAttempts": 104,
      "txHash": "0xc71c3fdb21b72e2b3f381013c090e536accfe0d304b02b0f41e9614fdce0b1fb"
    },
    {
      "turn": 44,
      "agent": "A",
      "gas": "1135673",
      "bankA": "217",
      "bankB": "155",
      "targetWord": "federal",
      "nccGuessCorrect": true,
      "vopAttempts": 3775,
      "txHash": "0xf67d2afcf293d16c6598e890eefb0167c91f8d96d794474857a1da5a732002ab"
    },
    {
      "turn": 45,
      "agent": "B",
      "gas": "1013822",
      "bankA": "213",
      "bankB": "155",
      "targetWord": "sorry",
      "nccGuessCorrect": true,
      "vopAttempts": 9953,
      "txHash": "0xe1f88883c1b22c1ee827e8d99d7da4457f99ad0ff71467ed10bd0d08a48956bd"
    },
    {
      "turn": 46,
      "agent": "A",
      "gas": "926476",
      "bankA": "213",
      "bankB": "125",
      "targetWord": "aware",
      "nccGuessCorrect": true,
      "vopAttempts": 981,
      "txHash": "0xad6d81ea104fca1f052d5c17a9f042cf3953badd7d0e3aaa6de34221323cccb7"
    },
    {
      "turn": 47,
      "agent": "B",
      "gas": "1063785",
      "bankA": "209",
      "bankB": "125",
      "targetWord": "silk",
      "nccGuessCorrect": true,
      "vopAttempts": 957,
      "txHash": "0x17aa0f2fbc0574db39b88b846e0bc234567177ae91bcc05911eb247aaf209d91"
    },
    {
      "turn": 48,
      "agent": "A",
      "gas": "924984",
      "bankA": "209",
      "bankB": "123",
      "targetWord": "circle",
      "nccGuessCorrect": true,
      "vopAttempts": 74,
      "txHash": "0x47b2ca22ed60de5e3777ecf0ccca78e5e4081d1e24d0e1a5eb1a5112ba09dcb9"
    },
    {
      "turn": 49,
      "agent": "B",
      "gas": "1196263",
      "bankA": "205",
      "bankB": "123",
      "targetWord": "pupil",
      "nccGuessCorrect": true,
      "vopAttempts": 501,
      "txHash": "0x9325527b117bdb0d1aff0bc5411478b4d1d57493544f99b7eb378265af6ee88c"
    },
    {
      "turn": 50,
      "agent": "A",
      "gas": "763026",
      "bankA": "205",
      "bankB": "121",
      "targetWord": "inhale",
      "nccGuessCorrect": true,
      "vopAttempts": 6,
      "txHash": "0xe3a49a681e19f4628d642eebb1ec361868780acfe26a2dc7247cd494e5526f11"
    },
    {
      "turn": 51,
      "agent": "B",
      "gas": "1183085",
      "bankA": "202",
      "bankB": "121",
      "targetWord": "city",
      "nccGuessCorrect": true,
      "vopAttempts": 902,
      "txHash": "0xfdd75502c57abcfc7cfb5dd838556b1157cae86984ebdcb3aa6e96d69847bcc0"
    },
    {
      "turn": 52,
      "agent": "A",
      "gas": "1370482",
      "bankA": "202",
      "bankB": "119",
      "targetWord": "virus",
      "nccGuessCorrect": true,
      "vopAttempts": 87,
      "txHash": "0xec334cc83b660c3892afac92b17bf4e42917cf4bafcf8e9ce145d02abf8f09a6"
    },
    {
      "turn": 53,
      "agent": "B",
      "gas": "1245790",
      "bankA": "199",
      "bankB": "119",
      "targetWord": "lonely",
      "nccGuessCorrect": true,
      "vopAttempts": 71,
      "txHash": "0x2a93ece6af2ec4f9b54af6b8a1c73c6b9e1ecdf5362dcf8b16242b2cdaed2ed4"
    },
    {
      "turn": 54,
      "agent": "A",
      "gas": "815617",
      "bankA": "199",
      "bankB": "117",
      "targetWord": "radar",
      "nccGuessCorrect": true,
      "vopAttempts": 854,
      "txHash": "0x8a9920c5f4da6db5cb7892202ffdaab9bc97dec3938981ee80911778b5caa4af"
    },
    {
      "turn": 55,
      "agent": "B",
      "gas": "453704",
      "bankA": "196",
      "bankB": "117",
      "targetWord": "absent",
      "nccGuessCorrect": true,
      "vopAttempts": 361,
      "txHash": "0x0c818268d8dbfb56d49863e024a045413fdc51fd8f3c3b6611bacafd0048bb5f"
    },
    {
      "turn": 56,
      "agent": "A",
      "gas": "616405",
      "bankA": "193",
      "bankB": "115",
      "targetWord": "behind",
      "nccGuessCorrect": true,
      "vopAttempts": 954,
      "txHash": "0x615331951fe98bc3f7f2b6e8e94f4238b56b17e2a8691a7f52b4a797ef7931b8"
    },
    {
      "turn": 57,
      "agent": "B",
      "gas": "692348",
      "bankA": "193",
      "bankB": "113",
      "targetWord": "fault",
      "nccGuessCorrect": true,
      "vopAttempts": 2397,
      "txHash": "0x1072f0625d07905d3a3cd91deb4ced679b1f330eadc04b1dca69ff9ded28b1f9"
    },
    {
      "turn": 58,
      "agent": "A",
      "gas": "976761",
      "bankA": "190",
      "bankB": "113",
      "targetWord": "boat",
      "nccGuessCorrect": true,
      "vopAttempts": 1112,
      "txHash": "0x81e8e5887cbe80915dc172f57f3f4a7b10baad8706a43784cdb900776bf986c6"
    },
    {
      "turn": 59,
      "agent": "B",
      "gas": "1576469",
      "bankA": "190",
      "bankB": "113",
      "targetWord": "spirit",
      "nccGuessCorrect": true,
      "vopAttempts": 37,
      "txHash": "0x0a68fb827a877e13f0e47e24a8a664904f45795ceae8679f7a91f5d3c08d80b4"
    },
    {
      "turn": 60,
      "agent": "A",
      "gas": "1348196",
      "bankA": "190",
      "bankB": "111",
      "targetWord": "style",
      "nccGuessCorrect": true,
      "vopAttempts": 1018,
      "txHash": "0x25be2972f0663382ee62948133432d99002fa2a056756498135057c6afcea953"
    },
    {
      "turn": 61,
      "agent": "B",
      "gas": "830883",
      "bankA": "187",
      "bankB": "109",
      "targetWord": "object",
      "nccGuessCorrect": false,
      "vopAttempts": 115,
      "txHash": "0x3f018cb86d2326981ab5919b571bf430d2f1f682a3cf304d71d7e8357b231c5c"
    },
    {
      "turn": 62,
      "agent": "A",
      "gas": "590438",
      "bankA": "187",
      "bankB": "109",
      "targetWord": "alley",
      "nccGuessCorrect": true,
      "vopAttempts": 389,
      "txHash": "0x80be69e64e5018e9d2f3e7650e728d1ed76cf3df2b4b5d006fec3b395f3b0741"
    },
    {
      "turn": 63,
      "agent": "B",
      "gas": "1000351",
      "bankA": "184",
      "bankB": "109",
      "targetWord": "flavor",
      "nccGuessCorrect": true,
      "vopAttempts": 215,
      "txHash": "0x09ed071d8a11763cb5cf1f53d74b56d2c8494ad7a60a5f9604dbd22693277b9f"
    },
    {
      "turn": 64,
      "agent": "A",
      "gas": "765681",
      "bankA": "184",
      "bankB": "79",
      "targetWord": "list",
      "nccGuessCorrect": true,
      "vopAttempts": 285,
      "txHash": "0xda986dc9e9722db4104e71932e74fbad98f07d65ab2c52cba24cc478b79482ba"
    },
    {
      "turn": 65,
      "agent": "B",
      "gas": "1151099",
      "bankA": "181",
      "bankB": "79",
      "targetWord": "brown",
      "nccGuessCorrect": true,
      "vopAttempts": 43,
      "txHash": "0x3859ad8e608ee1f4a08ab65983a69fa0e95636b4d2e135deed76a684f316d01d"
    },
    {
      "turn": 66,
      "agent": "A",
      "gas": "1288878",
      "bankA": "178",
      "bankB": "78",
      "targetWord": "visit",
      "nccGuessCorrect": true,
      "vopAttempts": 3744,
      "txHash": "0xba776be485aa51e46fd6273717f03517fbcb27f2778a26854bc6f8693c88ab12"
    },
    {
      "turn": 67,
      "agent": "B",
      "gas": "1295125",
      "bankA": "178",
      "bankB": "78",
      "targetWord": "grit",
      "nccGuessCorrect": true,
      "vopAttempts": 945,
      "txHash": "0xefba567dce5b6d5c072282af9b83fb7e1c0f6fa5661c6d3357032e2139ff6ff1"
    },
    {
      "turn": 68,
      "agent": "A",
      "gas": "1609917",
      "bankA": "175",
      "bankB": "77",
      "targetWord": "thing",
      "nccGuessCorrect": true,
      "vopAttempts": 1048,
      "txHash": "0x7d08653e53c0ab194136e34972bb09a37162fca6e59563903712ab7839e36976"
    },
    {
      "turn": 69,
      "agent": "B",
      "gas": "1698575",
      "bankA": "175",
      "bankB": "76",
      "targetWord": "upgrade",
      "nccGuessCorrect": false,
      "vopAttempts": 39,
      "txHash": "0x079592931498c78ca0e4af6e6ce1f87dd68d49d58737dbe628995a9612ef1812"
    },
    {
      "turn": 70,
      "agent": "A",
      "gas": "1251935",
      "bankA": "175",
      "bankB": "76",
      "targetWord": "trial",
      "nccGuessCorrect": true,
      "vopAttempts": 173,
      "txHash": "0x2c03464b05d6e8e1dae91b68f74a7acf1cef7c3c71bbb6775aec1fbc4201b7da"
    },
    {
      "turn": 71,
      "agent": "B",
      "gas": "1283280",
      "bankA": "172",
      "bankB": "76",
      "targetWord": "grit",
      "nccGuessCorrect": false,
      "vopAttempts": 249,
      "txHash": "0x5815fa04703b6d9aa210ba45280a1249e868fa198ff6a6f5a6192530f4cf09e4"
    },
    {
      "turn": 72,
      "agent": "A",
      "gas": "1042071",
      "bankA": "172",
      "bankB": "47",
      "targetWord": "swarm",
      "nccGuessCorrect": true,
      "vopAttempts": 5322,
      "txHash": "0x921d0cc4ca087aae6ee2691b41997bad4721c0dfc741139453e30de633b26cf9"
    },
    {
      "turn": 73,
      "agent": "B",
      "gas": "923458",
      "bankA": "169",
      "bankB": "18",
      "targetWord": "chat",
      "nccGuessCorrect": true,
      "vopAttempts": 3446,
      "txHash": "0x3b2333200b7174f18f0bb7ab6fca347785f81a011c3ecbb81c2ca697cb7522ee"
    },
    {
      "turn": 74,
      "agent": "A",
      "gas": "933117",
      "bankA": "169",
      "bankB": "18",
      "targetWord": "often",
      "nccGuessCorrect": true,
      "vopAttempts": 925,
      "txHash": "0xe4caddee75e23bb6df3020df53716bd57c23d0e55acfd15c7d12a73b2cf7c239"
    },
    {
      "turn": 75,
      "agent": "B",
      "gas": "589456",
      "bankA": "166",
      "bankB": "18",
      "targetWord": "donor",
      "nccGuessCorrect": true,
      "vopAttempts": 463,
      "txHash": "0x4b52b589fa6ddc1462437421b64c17894b6529d153e70aab06422fa4a0c06c80"
    },
    {
      "turn": 76,
      "agent": "A",
      "gas": "369607",
      "bankA": "166",
      "bankB": "17",
      "targetWord": "all",
      "nccGuessCorrect": true,
      "vopAttempts": 480,
      "txHash": "0xc5af3381990844044b34bd72b8936ba1f239237dc07d39a75c803f3c8ef5eea7"
    },
    {
      "turn": 77,
      "agent": "B",
      "gas": "1050890",
      "bankA": "163",
      "bankB": "17",
      "targetWord": "arch",
      "nccGuessCorrect": false,
      "vopAttempts": 299,
      "txHash": "0xc3fb9a775bb1933425772fafcbb8a91be8be25b4a9d6754adf49bf90d46de9e7"
    },
    {
      "turn": 78,
      "agent": "A",
      "gas": "1140308",
      "bankA": "163",
      "bankB": "16",
      "targetWord": "today",
      "nccGuessCorrect": true,
      "vopAttempts": 586,
      "txHash": "0x60535e8863293eb72b0dd06c29d39563285415a1b71f5eb7123c6ad27312a9c0"
    },
    {
      "turn": 79,
      "agent": "B",
      "gas": "117931",
      "bankA": "160",
      "bankB": "0",
      "targetWord": "double",
      "nccGuessCorrect": false,
      "vopAttempts": 6,
      "txHash": "0x8b08636e2503ef65350bad46a0da3a9e6b995f2c8c66735370320adf34b8d363"
    }
  ],
  "updatedAt": 1772344306901
}